pdata/__init__.py
pdata/_metadata.py
pdata/hdf5tools.py
pdata/helpers.py
pdata/jupyter_helpers.py
pdata/procedural_data.py
pdata/analysis/__init__.py
pdata/analysis/dataexplorer.py
pdata/analysis/dataview.py
proceduraldata-2.0.4.dist-info/LICENSE
proceduraldata-2.0.4.dist-info/METADATA
proceduraldata-2.0.4.dist-info/WHEEL
proceduraldata-2.0.4.dist-info/top_level.txt
proceduraldata-2.0.4.dist-info/RECORD
