Metadata-Version: 2.1
Name: proceduraldata
Version: 2.0.4
Summary: Simple-to-understand and robust data storage for experimental data
Home-page: https://pdata.readthedocs.io/
Author: Joonas Govenius
License: MIT
Classifier: Programming Language :: Python :: 3
Classifier: License :: OSI Approved :: MIT License
Classifier: Operating System :: OS Independent
Requires-Python: >=3.8
License-File: LICENSE
Requires-Dist: numpy
Requires-Dist: jsondiff
Requires-Dist: pytz
Requires-Dist: python-dateutil
Requires-Dist: requests
Requires-Dist: ipykernel
Requires-Dist: ipython
Requires-Dist: ipympl
Requires-Dist: ipylab
Requires-Dist: notebook
Requires-Dist: ipywidgets
Requires-Dist: matplotlib
Requires-Dist: uncertainties
Requires-Dist: xarray
